tikzpy/__init__.py
tikzpy/cls_canavas.py
tikzpy/cls_colors.py
tikzpy/cls_data.py
tikzpy/cls_labels.py
tikzpy/cls_plots.py
tikzpy/cls_points.py
tikzpy/cls_shapes.py
tikzpy/files_crawl.py
tikzpy/obj_data.py
tikzpy/tikz_py.py
tikzpy/buffer_data/__init__.py
tikzpy/buffer_data/cls_data_buffer.py
tikzpy/buffer_data/obj_data.py
tikzpy/plots/__init__.py
tikzpy/plots/cls_arrow_vertical.py
tikzpy/plots/cls_bars_vertical.py
tikzpy/plots/cls_racime.py
tikzpy/xpdftools_bin32/pdftopng.exe
tikzpy/xpdftools_bin32/pdftops.exe
tikzpy-0.0.4.dist-info/METADATA
tikzpy-0.0.4.dist-info/WHEEL
tikzpy-0.0.4.dist-info/license.txt
tikzpy-0.0.4.dist-info/top_level.txt
tikzpy-0.0.4.dist-info/zip-safe
tikzpy-0.0.4.dist-info/RECORD
