Metadata-Version: 2.1
Name: tikzpy
Version: 0.0.4
Summary: TikZpy simplifies the art of drawing by code tikz figures
Home-page: https://github.com/narfisaeu/tikzpy.git
Author: narfisaeu
Author-email: tikzpy@narfisa.eu
License: BSD 3-Clause License
Keywords: tikz,tikzpy,latex
Classifier: Programming Language :: Python :: 3
Classifier: License :: OSI Approved :: MIT License
Classifier: Operating System :: OS Independent
License-File: license.txt
Requires-Dist: numpy
Requires-Dist: matplotlib
